polylog/__init__.py
polylog/logger.py
tests/logger_test.py
tests/manual_logger_test.py
polylog-0.1.6.dist-info/METADATA
polylog-0.1.6.dist-info/WHEEL
polylog-0.1.6.dist-info/top_level.txt
polylog-0.1.6.dist-info/RECORD
