Metadata-Version: 2.1
Name: polylog
Version: 0.1.6
Summary: A custom python logging package
Home-page: https://github.com/lvlcn-t/PolyLog
Author: lvlcn-t
Author-email: lvlcn-t <75443136+lvlcn-t@users.noreply.github.com>
Maintainer-email: lvlcn-t <75443136+lvlcn-t@users.noreply.github.com>
Project-URL: Homepage, https://github.com/lvlcn-t/polylog
Project-URL: Bug Reports, https://github.com/lvlcn-t/polylog/issues
Project-URL: Source, https://github.com/lvlcn-t/polylog/
Classifier: Development Status :: 3 - Alpha
Classifier: Intended Audience :: Developers
Classifier: Topic :: Software Development :: Build Tools
Classifier: License :: OSI Approved :: MIT License
Classifier: Programming Language :: Python :: 3
Classifier: Programming Language :: Python :: 3.7
Classifier: Programming Language :: Python :: 3.8
Classifier: Programming Language :: Python :: 3.9
Classifier: Programming Language :: Python :: 3.10
Classifier: Programming Language :: Python :: 3.11
Classifier: Programming Language :: Python :: 3 :: Only
Requires-Python: >=3.8
Provides-Extra: dev
Requires-Dist: check-manifest ; extra == 'dev'
Provides-Extra: test
Requires-Dist: coverage ; extra == 'test'
